thinice/__init__.py
thinice/mainapi.py
thinice/thinice.py
thinice/version.py
thinice/cli/app.py
thinice/cli/debug.py
thinice/cli/delete.py
thinice/cli/download.py
thinice/cli/inventory.py
thinice/cli/jobs.py
thinice/cli/list.py
thinice/cli/main.py
thinice/cli/upload.py
thinice/cli/vaults.py
thinice/core/credentials.py
thinice/core/exceptions.py
thinice/core/inventory.py
thinice/core/locations.py
thinice/core/utils.py
thinice/core/vault.py
thinice/core/rawglacier/__init__.py
thinice/core/rawglacier/multipart.py
thinice-1.0.26.dist-info/METADATA
thinice-1.0.26.dist-info/WHEEL
thinice-1.0.26.dist-info/entry_points.txt
thinice-1.0.26.dist-info/licenses/LICENSE
thinice-1.0.26.dist-info/RECORD
