Metadata-Version: 2.3
Name: thinice
Version: 1.0.26
Summary: Human-friendly Amazon glacier API
Project-URL: Homepage, https://github.com/yaroslaff/ThinIce
Project-URL: Issues, https://github.com/yaroslaff/showcert/ThinIce
Author-email: Yaroslav Polyakov <yaroslaff@gmail.com>
License-File: LICENSE
Keywords: API,CLI,Glacier,aws,cold,cold storage,download,friendly,inventory,s4fs,storage,tool,upload,utility
Classifier: License :: OSI Approved :: MIT License
Classifier: Operating System :: OS Independent
Classifier: Programming Language :: Python :: 3
Requires-Python: >=3.9
Requires-Dist: boto3
Requires-Dist: fastapi
Requires-Dist: mypy-boto3-glacier
Requires-Dist: python-dotenv
Requires-Dist: rich
Requires-Dist: typer
Requires-Dist: uvicorn
